AUTHORS.txt
CHANGES.txt
LICENSE.txt
MANIFEST.in
README.txt
setup.py
jsb/__init__.py
jsb.recipe.jsonbot.egg-info/PKG-INFO
jsb.recipe.jsonbot.egg-info/SOURCES.txt
jsb.recipe.jsonbot.egg-info/dependency_links.txt
jsb.recipe.jsonbot.egg-info/entry_points.txt
jsb.recipe.jsonbot.egg-info/not-zip-safe
jsb.recipe.jsonbot.egg-info/requires.txt
jsb.recipe.jsonbot.egg-info/top_level.txt
jsb/recipe/__init__.py
jsb/recipe/download.py
jsb/recipe/utils.py
jsb/recipe/jsonbot/__init__.py
jsb/recipe/jsonbot/install.py
jsb/recipe/jsonbot/scripts/__init__.py