Metadata-Version: 1.0
Name: jsb.recipe.jsonbot
Version: 0.1a3
Summary: The bot for you!
Home-page: http://jsb-recipe.googlecode.com/
Author: Bart Thate
Author-email: bthate@gmail.com
License: MIT
Download-URL: http://code.google.com/p/jsb-recipe/downloads
Keywords: buildout recipe jsonbot jsb zc.buildout
Platform: UNKNOWN
Classifier: Development Status :: 3 - Alpha
Classifier: Environment :: Console
Classifier: Environment :: Other Environment
Classifier: Intended Audience :: Developers
Classifier: License :: OSI Approved :: MIT License
Classifier: Operating System :: Unix
Classifier: Operating System :: Other OS
Classifier: Programming Language :: Python
Classifier: Topic :: Communications :: Chat
Classifier: Topic :: Software Development :: Libraries :: Python Modules
